{
    "define_texts": {},
    "variables": {
        "1": {
            "voice_path1": "../idolmaster/sound/9900185/326630586cf879eb444a17449db11283.mp4",
            "voice_path2": "../idolmaster/sound/9900185/79cbfd31141f92213deb3806f30d9a10.mp4",
            "voice_path3": "../idolmaster/sound/9900185/590c1048c499601e5feb0da2cb1666cd.mp4",
            "voice_path4": "../idolmaster/sound/9900185/0ca6fb81376129b7e32b64c53ee43fc9.mp4",
            "voice_path5": "../idolmaster/sound/9900185/b6cfcad5de5be527a3cd19e8f7b371a3.mp4",
            "text_1_1": "みんな､幸せそうな笑顔でよかった",
            "text_1_2": "ですね､ﾌﾟﾛﾃﾞｭｰｻｰさん｡互いに助け",
            "text_1_3": "あって､こんなに素敵なﾊﾟｰﾃｨｰを企",
            "text_1_4": "画できたんです｡",
            "text_2_1": "よかったら､みんなをほめてあげて",
            "text_2_2": "ください｡……わ､私は､みんなより",
            "text_2_3": "少しお姉さんですから､大丈夫です",
            "text_2_4": "よっ｡",
            "text_3_1": "支える作業とかﾎﾟｼﾞｼｮﾝって､結構好",
            "text_3_2": "きなんです｡ほら､幹事とか､裏方のｽ",
            "text_3_3": "ﾀｯﾌとか｡ｱｲﾄﾞﾙになってからはでき",
            "text_3_4": "ませんけどね｡",
            "text_4_1": "ﾘｰﾀﾞｰなんて大層なﾎﾟｼﾞｼｮﾝはできま",
            "text_4_2": "せんけど……でも､私ががんばって､",
            "text_4_3": "みんなが笑顔になれるなら､やると",
            "text_4_4": "思いますよ｡",
            "text_5_1": "あっ､違いますからね｡やりたいわけ",
            "text_5_2": "じゃないんです｡……いえ､嫌なわけ",
            "text_5_3": "でもなくって､その､言葉のあやです",
            "text_5_4": "からっ! もうっ!",
            "name1": "美波",
            "msg2": "みんな､幸せそうな笑顔で\nよかったですね､ﾌﾟﾛﾃﾞｭｰｻｰさん｡\n互いに助けあって､こんなに素敵な\nﾊﾟｰﾃｨｰを企画できたんです｡",
            "msg3": "ちょっとくらい､みんなをほめて\nあげてください｡\n……わ､私は､みんなより少し\nお姉さんですから､大丈夫ですよっ｡",
            "msg4": "支える作業とかﾎﾟｼﾞｼｮﾝって､\n結構好きなんです｡ほら､幹事とか､\n裏方のｽﾀｯﾌとか｡ｱｲﾄﾞﾙになって\nからはできませんけどね｡",
            "msg5": "ﾘｰﾀﾞｰなんて大層なﾎﾟｼﾞｼｮﾝは\nできませんけど……でも､\n私ががんばって､みんなが笑顔に\nなれるなら､やると思いますよ｡",
            "msg6": "あっ､違いますからね｡やりたい\nわけじゃないんです｡……いえ､\n嫌なわけでもなくって､その､言葉\nのあやですからっ! もうっ!",
            "place_name": "ﾊﾟｰﾃｨｰ会場"
        }
    },
    "replace_font": false
}